rgd_fmv/__init__.py
rgd_fmv/apps.py
rgd_fmv/serializers.py
rgd_fmv/signals.py
rgd_fmv/urls.py
rgd_fmv/views.py
rgd_fmv/admin/__init__.py
rgd_fmv/admin/fmv.py
rgd_fmv/management/commands/_data_helper.py
rgd_fmv/management/commands/rgd_fmv_demo.py
rgd_fmv/management/commands/rgd_fmv_wasabi.py
rgd_fmv/migrations/0001_initial.py
rgd_fmv/migrations/0002_alter_fmv_status.py
rgd_fmv/migrations/__init__.py
rgd_fmv/models/__init__.py
rgd_fmv/models/base.py
rgd_fmv/rest/__init__.py
rgd_fmv/rest/viewsets.py
rgd_fmv/tasks/__init__.py
rgd_fmv/tasks/etl.py
rgd_fmv/tasks/jobs.py
rgd_fmv/templates/rgd_fmv/fmvmeta_detail.html
tests/__init__.py
tests/conftest.py
tests/data_fixtures.py
tests/factories.py
tests/manage.py
tests/test_demo_data.py
tests/test_fmv.py
tests/test_permissions.py
tests/test_rest.py
tests/test_project/__init__.py
tests/test_project/settings.py
tests/test_project/urls.py
django_rgd_fmv-0.3.11.dist-info/METADATA
django_rgd_fmv-0.3.11.dist-info/WHEEL
django_rgd_fmv-0.3.11.dist-info/top_level.txt
django_rgd_fmv-0.3.11.dist-info/RECORD
